gluon/__init__.py
gluon/_i18n.py
gluon/constants.py
gluon/context.py
gluon/policy.py
gluon/api/__init__.py
gluon/api/app.py
gluon/api/attributes.py
gluon/api/baseObject.py
gluon/api/link.py
gluon/api/proton_controller.py
gluon/api/root.py
gluon/api/types.py
gluon/api/hooks/__init__.py
gluon/api/hooks/context.py
gluon/api/hooks/policy_enforcement.py
gluon/api/views/__init__.py
gluon/api/views/versions.py
gluon/backends/__init__.py
gluon/backends/backend_base.py
gluon/backends/proton_client.py
gluon/backends/models/__init__.py
gluon/backends/models/net_l3vpn.py
gluon/cmd/__init__.py
gluon/cmd/api.py
gluon/cmd/api_tool.py
gluon/cmd/cli.py
gluon/common/__init__.py
gluon/common/exception.py
gluon/common/paths.py
gluon/common/service.py
gluon/conf/__init__.py
gluon/conf/config.py
gluon/conf/opts.py
gluon/db/__init__.py
gluon/db/api.py
gluon/db/sqlalchemy/__init__.py
gluon/db/sqlalchemy/api.py
gluon/db/sqlalchemy/models.py
gluon/managers/__init__.py
gluon/managers/manager_base.py
gluon/managers/models/__init__.py
gluon/managers/models/net_l3vpn.py
gluon/models/base/base.yaml
gluon/models/ietf-sfc/api.yaml
gluon/models/net-l3vpn/api.yaml
gluon/models/test/api.yaml
gluon/particleGenerator/ApiGenerator.py
gluon/particleGenerator/DataBaseModelGenerator.py
gluon/particleGenerator/PolicyGenerator.py
gluon/particleGenerator/__init__.py
gluon/particleGenerator/cli.py
gluon/particleGenerator/generator.py
gluon/plugin/__init__.py
gluon/plugin/core.py
gluon/policies/__init__.py
gluon/policies/base.py
gluon/policies/net_l3vpn.py
gluon/shim/README.txt
gluon/shim/__init__.py
gluon/shim/base.py
gluon/shim/main.py
gluon/shim/model.py
gluon/shim/utils.py
gluon/shim/api_models/__init__.py
gluon/shim/api_models/net_l3vpn.py
gluon/shim/backends/__init__.py
gluon/shim/backends/dummy_net_l3vpn.py
gluon/shim/backends/opendaylight/__init__.py
gluon/shim/backends/opendaylight/log.py
gluon-1.1.0.dist-info/DESCRIPTION.rst
gluon-1.1.0.dist-info/METADATA
gluon-1.1.0.dist-info/RECORD
gluon-1.1.0.dist-info/WHEEL
gluon-1.1.0.dist-info/entry_points.txt
gluon-1.1.0.dist-info/metadata.json
gluon-1.1.0.dist-info/pbr.json
gluon-1.1.0.dist-info/top_level.txt
